[{"score":null,"popularity":3,"translated":true,"adult":false,"language":"en","original_name":"Kickin' It Old Skool","name":"Kickin' It Old Skool","alternative_name":null,"movie_type":"movie","id":13280,"imdb_id":"tt0772178","url":"http://www.themoviedb.org/movie/13280","votes":0,"rating":0.0,"certification":"PG-13","overview":"\"Kickin' It Old Skool\" revolves around a 12-year-old breakdancer, who in 1986 hits his head while performing at a talent show and as a result is comatose for 20 years. He awakens to find he is a grown man. With the mind and experience of a young kid, he attempts to revive his and his dance team's short-lived career with the hopes of helping support his parents' failing yogurt shop.","released":"2007-04-27","posters":[{"image":{"type":"poster","size":"thumb","height":136,"width":92,"url":"http://cf2.imgobject.com/t/p/w92/tsEGWvqRypxdmgGuhokFxiDSwiz.jpg","id":"4ea6229c34f8633bdc004d63"}},{"image":{"type":"poster","size":"w154","height":228,"width":154,"url":"http://cf2.imgobject.com/t/p/w154/tsEGWvqRypxdmgGuhokFxiDSwiz.jpg","id":"4ea6229c34f8633bdc004d63"}},{"image":{"type":"poster","size":"cover","height":274,"width":185,"url":"http://cf2.imgobject.com/t/p/w185/tsEGWvqRypxdmgGuhokFxiDSwiz.jpg","id":"4ea6229c34f8633bdc004d63"}},{"image":{"type":"poster","size":"w342","height":506,"width":342,"url":"http://cf2.imgobject.com/t/p/w342/tsEGWvqRypxdmgGuhokFxiDSwiz.jpg","id":"4ea6229c34f8633bdc004d63"}},{"image":{"type":"poster","size":"mid","height":740,"width":500,"url":"http://cf2.imgobject.com/t/p/w500/tsEGWvqRypxdmgGuhokFxiDSwiz.jpg","id":"4ea6229c34f8633bdc004d63"}},{"image":{"type":"poster","size":"original","height":3000,"width":2026,"url":"http://cf2.imgobject.com/t/p/original/tsEGWvqRypxdmgGuhokFxiDSwiz.jpg","id":"4ea6229c34f8633bdc004d63"}}],"backdrops":[{"image":{"type":"backdrop","size":"thumb","height":169,"width":300,"url":"http://cf2.imgobject.com/t/p/w300/sBKzqF2vod6rK7ZandtunIAzd95.jpg","id":"4ea6229434f8633bdc004d5b"}},{"image":{"type":"backdrop","size":"poster","height":439,"width":780,"url":"http://cf2.imgobject.com/t/p/w780/sBKzqF2vod6rK7ZandtunIAzd95.jpg","id":"4ea6229434f8633bdc004d5b"}},{"image":{"type":"backdrop","size":"w1280","height":720,"width":1280,"url":"http://cf2.imgobject.com/t/p/w1280/sBKzqF2vod6rK7ZandtunIAzd95.jpg","id":"4ea6229434f8633bdc004d5b"}},{"image":{"type":"backdrop","size":"original","height":1080,"width":1920,"url":"http://cf2.imgobject.com/t/p/original/sBKzqF2vod6rK7ZandtunIAzd95.jpg","id":"4ea6229434f8633bdc004d5b"}}],"version":369,"last_modified_at":"2012-02-21 11:25:18 UTC"}]