[{"score":null,"popularity":3,"translated":true,"adult":false,"language":"en","original_name":"Code of the West","name":"Code of the West","alternative_name":null,"movie_type":"movie","id":70134,"imdb_id":"tt0039271","url":"http://www.themoviedb.org/movie/70134","votes":0,"rating":0.0,"certification":"","overview":"Knowing the railroad is coming, Carter is after the rancher's land. Bob and Chito return just in time to save Banker Stockton and his money from Carter's men. When Stockton then lends the ranchers money, Carter has them burned out. Bob knows Carter is responsible and when Carter's henchman Saunders is recognized, Bob goes into action.","released":"1947-02-20","posters":[{"image":{"type":"poster","size":"thumb","height":140,"width":92,"url":"http://cf2.imgobject.com/t/p/w92/i58VY5gDHShC5mtKskaMEONGzhE.jpg","id":"4ea6ba714f13c137cc00f525"}},{"image":{"type":"poster","size":"w154","height":235,"width":154,"url":"http://cf2.imgobject.com/t/p/w154/i58VY5gDHShC5mtKskaMEONGzhE.jpg","id":"4ea6ba714f13c137cc00f525"}},{"image":{"type":"poster","size":"cover","height":282,"width":185,"url":"http://cf2.imgobject.com/t/p/w185/i58VY5gDHShC5mtKskaMEONGzhE.jpg","id":"4ea6ba714f13c137cc00f525"}},{"image":{"type":"poster","size":"w342","height":522,"width":342,"url":"http://cf2.imgobject.com/t/p/w342/i58VY5gDHShC5mtKskaMEONGzhE.jpg","id":"4ea6ba714f13c137cc00f525"}},{"image":{"type":"poster","size":"mid","height":763,"width":500,"url":"http://cf2.imgobject.com/t/p/w500/i58VY5gDHShC5mtKskaMEONGzhE.jpg","id":"4ea6ba714f13c137cc00f525"}},{"image":{"type":"poster","size":"original","height":1831,"width":1200,"url":"http://cf2.imgobject.com/t/p/original/i58VY5gDHShC5mtKskaMEONGzhE.jpg","id":"4ea6ba714f13c137cc00f525"}}],"backdrops":[{"image":{"type":"backdrop","size":"thumb","height":169,"width":300,"url":"http://cf2.imgobject.com/t/p/w300/iSGwvY67N1TdpiQ3xeb2hgC3otp.jpg","id":"4ea6ba704f13c137cc00f523"}},{"image":{"type":"backdrop","size":"poster","height":439,"width":780,"url":"http://cf2.imgobject.com/t/p/w780/iSGwvY67N1TdpiQ3xeb2hgC3otp.jpg","id":"4ea6ba704f13c137cc00f523"}},{"image":{"type":"backdrop","size":"w1280","height":720,"width":1280,"url":"http://cf2.imgobject.com/t/p/w1280/iSGwvY67N1TdpiQ3xeb2hgC3otp.jpg","id":"4ea6ba704f13c137cc00f523"}},{"image":{"type":"backdrop","size":"original","height":720,"width":1280,"url":"http://cf2.imgobject.com/t/p/original/iSGwvY67N1TdpiQ3xeb2hgC3otp.jpg","id":"4ea6ba704f13c137cc00f523"}}],"version":79,"last_modified_at":"2012-02-23 02:26:59 UTC"}]