[{"score":null,"popularity":3,"translated":false,"adult":false,"language":"fr","original_name":"Good fences","name":"Good fences","alternative_name":null,"movie_type":"movie","id":61902,"imdb_id":"tt0326901","url":"http://www.themoviedb.org/movie/61902","votes":0,"rating":0.0,"certification":null,"overview":"Un procureur afro-américain réalise son rêve : devenir un avocat réputé dans un milieu où les blancs sont en majorité. Alors qu'il a quitté sa ville natale pour la ville de Greenwich depuis quelques semaines en compagnie de sa compagne et de ses deux enfants, il ne tarde pas à découvrir l'envers du décor. Le rêve de toute une vie se mue très vite en cauchemar...","released":"2004-10-04","posters":[],"backdrops":[],"version":51,"last_modified_at":"2012-01-01 11:13:45 UTC"}]