[{"score":null,"popularity":3,"translated":true,"adult":false,"language":"en","original_name":"What If","name":"What If","alternative_name":null,"movie_type":"movie","id":60006,"imdb_id":"tt1468387","url":"http://www.themoviedb.org/movie/60006","votes":0,"rating":0.0,"certification":"","overview":"Fifteen years ago, Ben Walker (Sorbo) made a decision to leave his college sweetheart Wendy (Swanson), and ultimately his faith, in order to pursue a lucrative business opportunity. Now on the verge of marriage to an equally materialistic fiance, he is visited by an angelic mechanic (Ratzenberger) who tells him that he needs to see what his life would have been like had he followed Gods calling. Suddenly, Ben finds himself married to Wendy with two daughters, including a rebellious teen (Ryan), getting ready for church on a Sunday morning, where hes scheduled to give his first sermon as the new pastor.  If Ben wants to get back to his old life, he must first learn to appreciate the value of faith and family, and perhaps rediscover the love of his life. In the tradition of Its a Wonderful Life and The Family Man, What If tells the story of a man whose glimpse into what hes missing reminds him of what he truly wants.","released":null,"posters":[{"image":{"type":"poster","size":"thumb","height":120,"width":92,"url":"http://cf2.imgobject.com/t/p/w92/w2tblR0EZVp7xA09XLBtA7PdI6B.jpg","id":"4f4189a019c29565c4008214"}},{"image":{"type":"poster","size":"w154","height":200,"width":154,"url":"http://cf2.imgobject.com/t/p/w154/w2tblR0EZVp7xA09XLBtA7PdI6B.jpg","id":"4f4189a019c29565c4008214"}},{"image":{"type":"poster","size":"cover","height":241,"width":185,"url":"http://cf2.imgobject.com/t/p/w185/w2tblR0EZVp7xA09XLBtA7PdI6B.jpg","id":"4f4189a019c29565c4008214"}},{"image":{"type":"poster","size":"w342","height":445,"width":342,"url":"http://cf2.imgobject.com/t/p/w342/w2tblR0EZVp7xA09XLBtA7PdI6B.jpg","id":"4f4189a019c29565c4008214"}},{"image":{"type":"poster","size":"mid","height":650,"width":500,"url":"http://cf2.imgobject.com/t/p/w500/w2tblR0EZVp7xA09XLBtA7PdI6B.jpg","id":"4f4189a019c29565c4008214"}},{"image":{"type":"poster","size":"original","height":866,"width":666,"url":"http://cf2.imgobject.com/t/p/original/w2tblR0EZVp7xA09XLBtA7PdI6B.jpg","id":"4f4189a019c29565c4008214"}}],"backdrops":[],"version":419,"last_modified_at":"2012-02-23 11:36:54 UTC"}]