[{"score":2.0374274,"popularity":3,"translated":true,"adult":false,"language":"en","original_name":"Chip 'n' Dale - Here Comes Trouble","name":"Chip 'n' Dale - Here Comes Trouble","alternative_name":"Vild Med Chip Og Chap","movie_type":"movie","id":49554,"imdb_id":null,"url":"http://www.themoviedb.org/movie/49554","votes":1,"rating":8.0,"certification":"G","overview":"The most mischievous characters to ever come out of Disney studios, Chip 'N' Dale are cute, cuddly and always in the centre of trouble. Here is a special collection of their Adventures that will have you and your family laughing again and again. It's double trouble in 'Chip 'N' Dale Go Nuts' when Donald tries to chop down their house for firewood, along with their supply of nuts. Then Chip 'N' Dale make themselves at home in Donald's train set in 'Out Of Scale'. It's romantic mayhem when Chip 'N' Dale like the same girl in 'Two Chips And A Miss'. In 'Food For Feudin\", Pluto wants to hide his bones in the same tree where Chip 'N' Dale store their acorns.","released":"2005-01-01","posters":[{"image":{"type":"poster","size":"thumb","height":138,"width":92,"url":"http://cf2.imgobject.com/t/p/w92/rU8Z4gNfrC3Db10O67EICRgmPEA.jpg","id":"4ea69a3f4f13c137cc00c3e7"}},{"image":{"type":"poster","size":"w154","height":231,"width":154,"url":"http://cf2.imgobject.com/t/p/w154/rU8Z4gNfrC3Db10O67EICRgmPEA.jpg","id":"4ea69a3f4f13c137cc00c3e7"}},{"image":{"type":"poster","size":"cover","height":278,"width":185,"url":"http://cf2.imgobject.com/t/p/w185/rU8Z4gNfrC3Db10O67EICRgmPEA.jpg","id":"4ea69a3f4f13c137cc00c3e7"}},{"image":{"type":"poster","size":"w342","height":513,"width":342,"url":"http://cf2.imgobject.com/t/p/w342/rU8Z4gNfrC3Db10O67EICRgmPEA.jpg","id":"4ea69a3f4f13c137cc00c3e7"}},{"image":{"type":"poster","size":"mid","height":750,"width":500,"url":"http://cf2.imgobject.com/t/p/w500/rU8Z4gNfrC3Db10O67EICRgmPEA.jpg","id":"4ea69a3f4f13c137cc00c3e7"}},{"image":{"type":"poster","size":"original","height":1500,"width":1000,"url":"http://cf2.imgobject.com/t/p/original/rU8Z4gNfrC3Db10O67EICRgmPEA.jpg","id":"4ea69a3f4f13c137cc00c3e7"}}],"backdrops":[{"image":{"type":"backdrop","size":"thumb","height":169,"width":300,"url":"http://cf2.imgobject.com/t/p/w300/9SkCUpvxCHSrAGOTPQvSrZkjJYx.jpg","id":"4ea69a444f13c137cc00c3ed"}},{"image":{"type":"backdrop","size":"poster","height":439,"width":780,"url":"http://cf2.imgobject.com/t/p/w780/9SkCUpvxCHSrAGOTPQvSrZkjJYx.jpg","id":"4ea69a444f13c137cc00c3ed"}},{"image":{"type":"backdrop","size":"w1280","height":720,"width":1280,"url":"http://cf2.imgobject.com/t/p/w1280/9SkCUpvxCHSrAGOTPQvSrZkjJYx.jpg","id":"4ea69a444f13c137cc00c3ed"}},{"image":{"type":"backdrop","size":"original","height":720,"width":1280,"url":"http://cf2.imgobject.com/t/p/original/9SkCUpvxCHSrAGOTPQvSrZkjJYx.jpg","id":"4ea69a444f13c137cc00c3ed"}}],"version":50,"last_modified_at":"2012-02-20 19:11:23 UTC"}]