[{"score":null,"popularity":3,"translated":true,"adult":false,"language":"en","original_name":"Send Me No Flowers","name":"Send Me No Flowers","alternative_name":null,"movie_type":"movie","id":4939,"imdb_id":"tt0058571","url":"http://www.themoviedb.org/movie/4939","votes":0,"rating":5.6,"certification":"","overview":"When he mistakenly thinks he's dying, a hypochondriac tries to choose his wife's next husband.","released":"1964-10-14","posters":[{"image":{"type":"poster","size":"thumb","height":141,"width":92,"url":"http://cf2.imgobject.com/t/p/w92/uPKMszsB8ZABEch2dIo767Mnnq7.jpg","id":"4ea5f7334f13c137cc002261"}},{"image":{"type":"poster","size":"w154","height":236,"width":154,"url":"http://cf2.imgobject.com/t/p/w154/uPKMszsB8ZABEch2dIo767Mnnq7.jpg","id":"4ea5f7334f13c137cc002261"}},{"image":{"type":"poster","size":"cover","height":284,"width":185,"url":"http://cf2.imgobject.com/t/p/w185/uPKMszsB8ZABEch2dIo767Mnnq7.jpg","id":"4ea5f7334f13c137cc002261"}},{"image":{"type":"poster","size":"w342","height":525,"width":342,"url":"http://cf2.imgobject.com/t/p/w342/uPKMszsB8ZABEch2dIo767Mnnq7.jpg","id":"4ea5f7334f13c137cc002261"}},{"image":{"type":"poster","size":"mid","height":767,"width":500,"url":"http://cf2.imgobject.com/t/p/w500/uPKMszsB8ZABEch2dIo767Mnnq7.jpg","id":"4ea5f7334f13c137cc002261"}},{"image":{"type":"poster","size":"original","height":1688,"width":1100,"url":"http://cf2.imgobject.com/t/p/original/uPKMszsB8ZABEch2dIo767Mnnq7.jpg","id":"4ea5f7334f13c137cc002261"}}],"backdrops":[{"image":{"type":"backdrop","size":"thumb","height":169,"width":300,"url":"http://cf2.imgobject.com/t/p/w300/6Zqw7NyvBqMP0G0m1fVeBLaFeQm.jpg","id":"4ebc03be5e73d61479001378"}},{"image":{"type":"backdrop","size":"poster","height":439,"width":780,"url":"http://cf2.imgobject.com/t/p/w780/6Zqw7NyvBqMP0G0m1fVeBLaFeQm.jpg","id":"4ebc03be5e73d61479001378"}},{"image":{"type":"backdrop","size":"w1280","height":720,"width":1280,"url":"http://cf2.imgobject.com/t/p/w1280/6Zqw7NyvBqMP0G0m1fVeBLaFeQm.jpg","id":"4ebc03be5e73d61479001378"}},{"image":{"type":"backdrop","size":"original","height":1080,"width":1920,"url":"http://cf2.imgobject.com/t/p/original/6Zqw7NyvBqMP0G0m1fVeBLaFeQm.jpg","id":"4ebc03be5e73d61479001378"}}],"version":311,"last_modified_at":"2012-02-23 12:27:49 UTC"}]