[{"score":1.9867852,"popularity":3,"translated":true,"adult":false,"language":"en","original_name":"Naisu no mori: The First Contact","name":"Funky Forest: The First Contact","alternative_name":"Funky Forest: The First Contact","movie_type":"movie","id":21136,"imdb_id":"tt0451829","url":"http://www.themoviedb.org/movie/21136","votes":0,"rating":0.0,"certification":"","overview":"Taste of Tea director Katsuhito Ishii collaborates with filmmakers Shinichiro Miki and Hajime Ishimine) for this outrageous collection of surreal, short attention span non-sequiturs largely revolving around Guitar Brother","released":"2005-10-25","posters":[{"image":{"type":"poster","size":"thumb","height":132,"width":92,"url":"http://cf2.imgobject.com/t/p/w92/1pO5Av3fglb63C3hETfaMJokjxQ.jpg","id":"4ea6486a9dc3d83c3b00694b"}},{"image":{"type":"poster","size":"w154","height":220,"width":154,"url":"http://cf2.imgobject.com/t/p/w154/1pO5Av3fglb63C3hETfaMJokjxQ.jpg","id":"4ea6486a9dc3d83c3b00694b"}},{"image":{"type":"poster","size":"cover","height":265,"width":185,"url":"http://cf2.imgobject.com/t/p/w185/1pO5Av3fglb63C3hETfaMJokjxQ.jpg","id":"4ea6486a9dc3d83c3b00694b"}},{"image":{"type":"poster","size":"w342","height":489,"width":342,"url":"http://cf2.imgobject.com/t/p/w342/1pO5Av3fglb63C3hETfaMJokjxQ.jpg","id":"4ea6486a9dc3d83c3b00694b"}},{"image":{"type":"poster","size":"mid","height":715,"width":500,"url":"http://cf2.imgobject.com/t/p/w500/1pO5Av3fglb63C3hETfaMJokjxQ.jpg","id":"4ea6486a9dc3d83c3b00694b"}},{"image":{"type":"poster","size":"original","height":768,"width":537,"url":"http://cf2.imgobject.com/t/p/original/1pO5Av3fglb63C3hETfaMJokjxQ.jpg","id":"4ea6486a9dc3d83c3b00694b"}}],"backdrops":[{"image":{"type":"backdrop","size":"thumb","height":169,"width":300,"url":"http://cf2.imgobject.com/t/p/w300/gVFfC15JcZDgsxinI7TdY3Ol72L.jpg","id":"4ea648689dc3d83c3b006949"}},{"image":{"type":"backdrop","size":"poster","height":439,"width":780,"url":"http://cf2.imgobject.com/t/p/w780/gVFfC15JcZDgsxinI7TdY3Ol72L.jpg","id":"4ea648689dc3d83c3b006949"}},{"image":{"type":"backdrop","size":"w1280","height":720,"width":1280,"url":"http://cf2.imgobject.com/t/p/w1280/gVFfC15JcZDgsxinI7TdY3Ol72L.jpg","id":"4ea648689dc3d83c3b006949"}},{"image":{"type":"backdrop","size":"original","height":576,"width":1024,"url":"http://cf2.imgobject.com/t/p/original/gVFfC15JcZDgsxinI7TdY3Ol72L.jpg","id":"4ea648689dc3d83c3b006949"}}],"version":130,"last_modified_at":"2012-02-20 17:06:45 UTC"}]