[{"score":null,"popularity":3,"translated":true,"adult":false,"language":"en","original_name":"House Calls","name":"House Calls","alternative_name":null,"movie_type":"movie","id":36361,"imdb_id":"tt0077699","url":"http://www.themoviedb.org/movie/36361","votes":0,"rating":0.0,"certification":"","overview":"Charley is a surgeon who's recently lost his wife; he embarks on a tragicomic romantic quest with one woman after another until he meets up with Ann, a singular woman, closer to his own age, who immediately and unexpectedly captures his heart.","released":"1978-03-15","posters":[{"image":{"type":"poster","size":"thumb","height":138,"width":92,"url":"http://cf2.imgobject.com/t/p/w92/9FY6Lm1FHIqKd0RDmGZWyHnaWG5.jpg","id":"4ea676189dc3d83c3b009539"}},{"image":{"type":"poster","size":"w154","height":231,"width":154,"url":"http://cf2.imgobject.com/t/p/w154/9FY6Lm1FHIqKd0RDmGZWyHnaWG5.jpg","id":"4ea676189dc3d83c3b009539"}},{"image":{"type":"poster","size":"cover","height":278,"width":185,"url":"http://cf2.imgobject.com/t/p/w185/9FY6Lm1FHIqKd0RDmGZWyHnaWG5.jpg","id":"4ea676189dc3d83c3b009539"}},{"image":{"type":"poster","size":"w342","height":513,"width":342,"url":"http://cf2.imgobject.com/t/p/w342/9FY6Lm1FHIqKd0RDmGZWyHnaWG5.jpg","id":"4ea676189dc3d83c3b009539"}},{"image":{"type":"poster","size":"mid","height":750,"width":500,"url":"http://cf2.imgobject.com/t/p/w500/9FY6Lm1FHIqKd0RDmGZWyHnaWG5.jpg","id":"4ea676189dc3d83c3b009539"}},{"image":{"type":"poster","size":"original","height":1500,"width":1000,"url":"http://cf2.imgobject.com/t/p/original/9FY6Lm1FHIqKd0RDmGZWyHnaWG5.jpg","id":"4ea676189dc3d83c3b009539"}}],"backdrops":[{"image":{"type":"backdrop","size":"thumb","height":169,"width":300,"url":"http://cf2.imgobject.com/t/p/w300/cXEMOQL46vKzOdyB28ZiCKzQ3rf.jpg","id":"4ea676199dc3d83c3b00953b"}},{"image":{"type":"backdrop","size":"poster","height":439,"width":780,"url":"http://cf2.imgobject.com/t/p/w780/cXEMOQL46vKzOdyB28ZiCKzQ3rf.jpg","id":"4ea676199dc3d83c3b00953b"}},{"image":{"type":"backdrop","size":"w1280","height":720,"width":1280,"url":"http://cf2.imgobject.com/t/p/w1280/cXEMOQL46vKzOdyB28ZiCKzQ3rf.jpg","id":"4ea676199dc3d83c3b00953b"}},{"image":{"type":"backdrop","size":"original","height":720,"width":1280,"url":"http://cf2.imgobject.com/t/p/original/cXEMOQL46vKzOdyB28ZiCKzQ3rf.jpg","id":"4ea676199dc3d83c3b00953b"}}],"version":256,"last_modified_at":"2012-02-22 16:08:09 UTC"}]