[{"score":2.4263182,"popularity":3,"translated":true,"adult":false,"language":"en","original_name":"Jack & Sarah","name":"Jack & Sarah","alternative_name":"Jack & Sarah","movie_type":"movie","id":2021,"imdb_id":"tt0113448","url":"http://www.themoviedb.org/movie/2021","votes":0,"rating":7.4,"certification":"","overview":"Jack always lands on his feet. He lands on his feet when he marries the beautiful Sarah. He lands on his feet when he buys a luxurious new home. However, when Sarah goes into labour, he takes a tumble down the stairs and lands on his head. When he comes around he discovers he is the proud father of a baby girl, but deficient in the spouse department to the tune of 1. The hires the help of a novice","released":"1995-06-02","posters":[{"image":{"type":"poster","size":"thumb","height":135,"width":92,"url":"http://cf2.imgobject.com/t/p/w92/9FlsWsHPGiGobe9vblJNhNYJS5d.jpg","id":"4ea5e7459dc3d83c3b001627"}},{"image":{"type":"poster","size":"w154","height":225,"width":154,"url":"http://cf2.imgobject.com/t/p/w154/9FlsWsHPGiGobe9vblJNhNYJS5d.jpg","id":"4ea5e7459dc3d83c3b001627"}},{"image":{"type":"poster","size":"cover","height":271,"width":185,"url":"http://cf2.imgobject.com/t/p/w185/9FlsWsHPGiGobe9vblJNhNYJS5d.jpg","id":"4ea5e7459dc3d83c3b001627"}},{"image":{"type":"poster","size":"w342","height":500,"width":342,"url":"http://cf2.imgobject.com/t/p/w342/9FlsWsHPGiGobe9vblJNhNYJS5d.jpg","id":"4ea5e7459dc3d83c3b001627"}},{"image":{"type":"poster","size":"mid","height":732,"width":500,"url":"http://cf2.imgobject.com/t/p/w500/9FlsWsHPGiGobe9vblJNhNYJS5d.jpg","id":"4ea5e7459dc3d83c3b001627"}},{"image":{"type":"poster","size":"original","height":1463,"width":1000,"url":"http://cf2.imgobject.com/t/p/original/9FlsWsHPGiGobe9vblJNhNYJS5d.jpg","id":"4ea5e7459dc3d83c3b001627"}}],"backdrops":[{"image":{"type":"backdrop","size":"thumb","height":169,"width":300,"url":"http://cf2.imgobject.com/t/p/w300/lWwZdXneO2XA26HaNL8akwVH0Qw.jpg","id":"4ea5e7429dc3d83c3b001625"}},{"image":{"type":"backdrop","size":"poster","height":439,"width":780,"url":"http://cf2.imgobject.com/t/p/w780/lWwZdXneO2XA26HaNL8akwVH0Qw.jpg","id":"4ea5e7429dc3d83c3b001625"}},{"image":{"type":"backdrop","size":"w1280","height":720,"width":1280,"url":"http://cf2.imgobject.com/t/p/w1280/lWwZdXneO2XA26HaNL8akwVH0Qw.jpg","id":"4ea5e7429dc3d83c3b001625"}},{"image":{"type":"backdrop","size":"original","height":720,"width":1280,"url":"http://cf2.imgobject.com/t/p/original/lWwZdXneO2XA26HaNL8akwVH0Qw.jpg","id":"4ea5e7429dc3d83c3b001625"}}],"version":282,"last_modified_at":"2012-02-22 18:07:33 UTC"}]